async_processor/__init__.py
async_processor/amqp_pub_sub.py
async_processor/app.py
async_processor/function_service/README.md
async_processor/function_service/__init__.py
async_processor/function_service/async_function_deployment.py
async_processor/function_service/utils.py
async_processor/kafka_pub_sub.py
async_processor/logger.py
async_processor/nats_pub_sub.py
async_processor/processor.py
async_processor/prometheus_metrics.py
async_processor/pydantic_v1.py
async_processor/sidecar/__init__.py
async_processor/sidecar/sidecar.py
async_processor/sidecar/types.py
async_processor/sqs_pub_sub.py
async_processor/types.py
async_processor/worker.py
async_processor-1.1.0.dist-info/LICENSE
async_processor-1.1.0.dist-info/METADATA
async_processor-1.1.0.dist-info/WHEEL
async_processor-1.1.0.dist-info/RECORD
