Metadata-Version: 2.3
Name: async-processor
Version: 1.1.0
Summary: 
Author: debajyoti-truefoundry
Author-email: debajyoti@truefoundry.com
Requires-Python: >=3.8,<3.13
Classifier: Programming Language :: Python :: 3
Classifier: Programming Language :: Python :: 3.8
Classifier: Programming Language :: Python :: 3.9
Classifier: Programming Language :: Python :: 3.10
Classifier: Programming Language :: Python :: 3.11
Classifier: Programming Language :: Python :: 3.12
Provides-Extra: amqp
Provides-Extra: kafka
Provides-Extra: nats
Provides-Extra: sqs
Requires-Dist: aio-pika (>=9.4.0,<10.0.0) ; extra == "amqp"
Requires-Dist: aiohttp (>=3.8.6,<3.11.0)
Requires-Dist: boto3 (>=1.28.16,<1.29.0) ; extra == "sqs"
Requires-Dist: cryptography (>=41.0.6,<43.1.0)
Requires-Dist: fastapi (>=0.93.0,<0.116.0)
Requires-Dist: gunicorn (>=21.2.0,<24.0.0)
Requires-Dist: kafka-python[crc32c,lz4,snappy,zstd] (>=2.2.0,<2.3.0) ; extra == "kafka"
Requires-Dist: nats-py (==2.6.0) ; extra == "nats"
Requires-Dist: orjson (>=3.9.2,<3.10.0)
Requires-Dist: prometheus_client (>=0.17.1,<0.18.0)
Requires-Dist: pydantic (>=1.10.12,<2.10.0)
Requires-Dist: requests (>=2.31.0,<2.33.0)
Requires-Dist: starlette (>=0.27.0,<0.42.0)
Requires-Dist: urllib3 (>=1.26.18,<2.0.0)
Requires-Dist: uvicorn (>=0.23.2,<0.32.0)
